{
  "header": {
    "logo": "АШ",
    "name": "Антон Шага",
    "home": "Главная",
    "about": "Обо мне",
    "projects": "Проекты",
    "skills": "Навыки",
    "experience": "Опыт",
    "contact": "Контакты",
    "resume": "Резюме"
  },
  "hero": {
    "name": "Антон Шага",
    "title": "Фронтенд Разработчик",
    "description": "Создаю современные, отзывчивые и производительные веб-приложения с использованием React, Next.js и современных фронтенд-технологий.",
    "contact":"Связаться",
    "projects":"Мои проекты"
  }
}
